json_schema_generator2/__init__.py
json_schema_generator2/generator.py
json_schema_generator2/types.py
json_schema_generator2-0.1.15.dist-info/METADATA
json_schema_generator2-0.1.15.dist-info/WHEEL
json_schema_generator2-0.1.15.dist-info/entry_points.txt
json_schema_generator2-0.1.15.dist-info/top_level.txt
json_schema_generator2-0.1.15.dist-info/RECORD
