Metadata-Version: 2.1
Name: json-schema-generator2
Version: 0.1.15
Summary: Pretty print json contains python style coments, string literal.
Home-page: https://github.com/weaming/json-schema-generator
Author: weaming
Author-email: garden.yuen@gmail.com
License: UNKNOWN
Project-URL: Source, https://github.com/weaming/json-schema-generator
Project-URL: Bug Reports, https://github.com/weaming/json-schema-generator
Keywords: json format
Platform: UNKNOWN
Requires-Dist: pretty-format-json
